{
  "meta": {
    "snapshotId": "source-health",
    "description": "Per (sourceId, companyId) probe of source reachability and freshness.",
    "generatedAt": "2026-05-12T16:11:00.280Z",
    "rowCount": 8,
    "status": "ok",
    "notes": null,
    "source": {
      "sourceClass": "derived",
      "sourceUrl": null,
      "sourceLabel": "Derived from discovery adapter results",
      "fetchedAt": "2026-05-12T16:11:00.280Z",
      "publishedAt": null,
      "notes": null
    },
    "errors": []
  },
  "rows": [
    {
      "sourceId": "nse",
      "companyId": "tcs",
      "checkedAt": "2026-05-12T16:11:00.121Z",
      "status": "blocked",
      "filingsDiscovered": 0,
      "latestFilingDate": null,
      "errorMessage": "NSE HTTP 403",
      "notes": "Source returned an error; see errorMessage."
    },
    {
      "sourceId": "bse",
      "companyId": "tcs",
      "checkedAt": "2026-05-12T16:11:00.225Z",
      "status": "blocked",
      "filingsDiscovered": 0,
      "latestFilingDate": null,
      "errorMessage": "BSE HTTP 403",
      "notes": "Source returned an error; see errorMessage."
    },
    {
      "sourceId": "nse",
      "companyId": "infosys",
      "checkedAt": "2026-05-12T16:11:00.253Z",
      "status": "blocked",
      "filingsDiscovered": 0,
      "latestFilingDate": null,
      "errorMessage": "NSE HTTP 403",
      "notes": "Source returned an error; see errorMessage."
    },
    {
      "sourceId": "bse",
      "companyId": "infosys",
      "checkedAt": "2026-05-12T16:11:00.258Z",
      "status": "blocked",
      "filingsDiscovered": 0,
      "latestFilingDate": null,
      "errorMessage": "BSE HTTP 403",
      "notes": "Source returned an error; see errorMessage."
    },
    {
      "sourceId": "nse",
      "companyId": "hcltech",
      "checkedAt": "2026-05-12T16:11:00.262Z",
      "status": "blocked",
      "filingsDiscovered": 0,
      "latestFilingDate": null,
      "errorMessage": "NSE HTTP 403",
      "notes": "Source returned an error; see errorMessage."
    },
    {
      "sourceId": "bse",
      "companyId": "hcltech",
      "checkedAt": "2026-05-12T16:11:00.266Z",
      "status": "blocked",
      "filingsDiscovered": 0,
      "latestFilingDate": null,
      "errorMessage": "BSE HTTP 403",
      "notes": "Source returned an error; see errorMessage."
    },
    {
      "sourceId": "nse",
      "companyId": "wipro",
      "checkedAt": "2026-05-12T16:11:00.270Z",
      "status": "blocked",
      "filingsDiscovered": 0,
      "latestFilingDate": null,
      "errorMessage": "NSE HTTP 403",
      "notes": "Source returned an error; see errorMessage."
    },
    {
      "sourceId": "bse",
      "companyId": "wipro",
      "checkedAt": "2026-05-12T16:11:00.274Z",
      "status": "blocked",
      "filingsDiscovered": 0,
      "latestFilingDate": null,
      "errorMessage": "BSE HTTP 403",
      "notes": "Source returned an error; see errorMessage."
    }
  ]
}
